dijkprofile_annotator/__init__.py
dijkprofile_annotator/__main__.py
dijkprofile_annotator/_version.py
dijkprofile_annotator/annotator.py
dijkprofile_annotator/config.py
dijkprofile_annotator/app/__init__.py
dijkprofile_annotator/app/app.py
dijkprofile_annotator/data/trained_models/dijknet_simple_95.pt
dijkprofile_annotator/data/trained_models/scaler.pik
dijkprofile_annotator/datasets/__init__.py
dijkprofile_annotator/datasets/dataset.py
dijkprofile_annotator/models/__init__.py
dijkprofile_annotator/models/dijknet.py
dijkprofile_annotator/preprocessing/__init__.py
dijkprofile_annotator/preprocessing/preprocessing.py
dijkprofile_annotator/training/__init__.py
dijkprofile_annotator/training/train.py
dijkprofile_annotator/utils/__init__.py
dijkprofile_annotator/utils/utils.py
dijkprofile_annotator-0.1.5.dist-info/LICENSE
dijkprofile_annotator-0.1.5.dist-info/METADATA
dijkprofile_annotator-0.1.5.dist-info/WHEEL
dijkprofile_annotator-0.1.5.dist-info/entry_points.txt
dijkprofile_annotator-0.1.5.dist-info/top_level.txt
dijkprofile_annotator-0.1.5.dist-info/RECORD
