Metadata-Version: 2.1
Name: dijkprofile-annotator
Version: 0.1.5
Summary: Automatically annotate dijkprofiles in qDAMEdit format
Home-page: https://gitlab.com/hetwaterschapshuis/kenniscentrum/tooling/dijkprofile-annotator
Author: Jonathan Gerbscheid
Author-email: j.gerbscheid@hetwaterschapshuis.nl
Maintainer: Jonathan Gerbscheid
Maintainer-email: j.gerbscheid@hetwaterschapshuis.nl
License: MIT
Project-URL: Bug Tracker, https://gitlab.com/hetwaterschapshuis/kenniscentrum/tooling/dijkprofile-annotator/-/issues
Project-URL: Source Code, https://gitlab.com/hetwaterschapshuis/kenniscentrum/tooling/dijkprofile-annotator/-/tree/master
Platform: UNKNOWN
Requires-Python: >=3.6
License-File: LICENSE
Requires-Dist: joblib (>=1.1.0)
Requires-Dist: numpy (>=1.21.4)
Requires-Dist: Pillow (>=8.4.0)
Requires-Dist: scikit-learn (>=1.0.1)
Requires-Dist: torch (>=1.9.0)
Requires-Dist: matplotlib (>=3.4.3)
Requires-Dist: seaborn
Requires-Dist: tqdm
Requires-Dist: Jinja2 (>=3.0)
Requires-Dist: gradio
Provides-Extra: interactive
Requires-Dist: jupyter ; extra == 'interactive'
